qutip_jax/__init__.py
qutip_jax/binops.py
qutip_jax/convert.py
qutip_jax/create.py
qutip_jax/family.py
qutip_jax/jaxarray.py
qutip_jax/jaxdia.py
qutip_jax/linalg.py
qutip_jax/measurements.py
qutip_jax/norm.py
qutip_jax/ode.py
qutip_jax/permute.py
qutip_jax/properties.py
qutip_jax/qobjevo.py
qutip_jax/qutip_trees.py
qutip_jax/reshape.py
qutip_jax/settings.py
qutip_jax/unary.py
qutip_jax/version.py
qutip_jax-0.1.1.dist-info/licenses/LICENSE.txt
qutip_jax-0.1.1.dist-info/METADATA
qutip_jax-0.1.1.dist-info/WHEEL
qutip_jax-0.1.1.dist-info/entry_points.txt
qutip_jax-0.1.1.dist-info/top_level.txt
qutip_jax-0.1.1.dist-info/RECORD
