Metadata-Version: 2.4
Name: qutip-jax
Version: 0.1.1
Summary: JAX backend for QuTiP
Home-page: https://qutip.org
Author: Eric Giguere, Rochisha Agarwal, Shahnawaz Ahmed
Author-email: qutip-admin@googlegroups.com
License: BSD 3-Clause License
Keywords: quantum,physics,dynamics,gpu,linear-algebra
Platform: Linux
Platform: Mac OSX
Platform: Unix
Platform: Windows
Classifier: Development Status :: 2 - Pre-Alpha
Classifier: Intended Audience :: Science/Research
Classifier: License :: OSI Approved :: BSD License
Classifier: Programming Language :: Python
Classifier: Programming Language :: Python :: 3
Classifier: Topic :: Scientific/Engineering
Classifier: Operating System :: MacOS
Classifier: Operating System :: POSIX
Classifier: Operating System :: Unix
Classifier: Operating System :: Microsoft :: Windows
License-File: LICENSE.txt
Requires-Dist: qutip>=5.1.0
Requires-Dist: jax
Requires-Dist: diffrax
Requires-Dist: equinox
Provides-Extra: tests
Requires-Dist: pytest>=6.0; extra == "tests"
Provides-Extra: full
Requires-Dist: pytest>=6.0; extra == "full"
Dynamic: license-file
